tailestim/__about__.py
tailestim/__init__.py
tailestim/datasets.py
tailestim/data/CAIDA_KONECT.dat
tailestim/data/Libimseti_in_KONECT.dat
tailestim/data/Pareto.dat
tailestim/estimators/__init__.py
tailestim/estimators/base.py
tailestim/estimators/bulk_fit.py
tailestim/estimators/estimator_set.py
tailestim/estimators/hill.py
tailestim/estimators/kernel.py
tailestim/estimators/moments.py
tailestim/estimators/pickands.py
tailestim/estimators/result.py
tailestim/estimators/smooth_hill.py
tailestim/estimators/tail_methods.py
tailestim/estimators/plot/plot_methods.py
tailestim-0.6.0.dist-info/METADATA
tailestim-0.6.0.dist-info/WHEEL
tailestim-0.6.0.dist-info/licenses/LICENSE.txt
tailestim-0.6.0.dist-info/RECORD
