Metadata-Version: 2.4
Name: tailestim
Version: 0.6.0
Summary: A Python package for estimating tail parameters of heavy-tailed distributions, which is useful for analyzing power-law behavior in complex networks.
Project-URL: Documentation, https://tailestim.readthedocs.io/en/latest/index.html
Project-URL: Issues, https://github.com/mu373/tailestim/issues
Project-URL: Source, https://github.com/mu373/tailestim
Author-email: Minami Ueda <minami.ueda@gmail.com>
License-Expression: MIT
License-File: LICENSE.txt
Keywords: complex-network,heavy-tail,network-science,power-law
Classifier: Development Status :: 3 - Alpha
Classifier: Programming Language :: Python
Classifier: Programming Language :: Python :: 3.8
Classifier: Programming Language :: Python :: 3.9
Classifier: Programming Language :: Python :: 3.10
Classifier: Programming Language :: Python :: 3.11
Classifier: Programming Language :: Python :: 3.12
Classifier: Programming Language :: Python :: 3.13
Requires-Python: >=3.6
Requires-Dist: matplotlib>=3.5
Requires-Dist: numpy>=1.19
